ibdx/__init__.py
ibdx/__main__.py
ibdx/cli.py
ibdx/deps.py
ibdx/ibd_backup.py
ibdx/ibd_restore.py
ibdx/mysql_db_quick.py
ibdx-0.5.1.dist-info/METADATA
ibdx-0.5.1.dist-info/WHEEL
ibdx-0.5.1.dist-info/entry_points.txt
ibdx-0.5.1.dist-info/licenses/LICENSE
ibdx-0.5.1.dist-info/RECORD
