Metadata-Version: 2.3
Name: ibdx
Version: 0.5.1
Summary: yet another backup/restore program for mysql InnoDB tables
Project-URL: homepage, https://github.com/Grvzard/ibdx
License-File: LICENSE
Requires-Python: >=3.8
Requires-Dist: pymysql==1.1.1
Requires-Dist: typer<1.0.0,>=0.7.0
